examples/__init__.py
examples/crawler/__init__.py
python_workflow/__init__.py
tests/__init__.py
tests/test_step.py
tests/test_task.py
tests/test_workflow.py
python_workflow-1.0.3.dist-info/LICENSE
python_workflow-1.0.3.dist-info/METADATA
python_workflow-1.0.3.dist-info/WHEEL
python_workflow-1.0.3.dist-info/top_level.txt
python_workflow-1.0.3.dist-info/RECORD
