Metadata-Version: 2.1
Name: python-workflow
Version: 1.0.3
Summary: UNKNOWN
Home-page: https://anthonykgross.fr/python-workflow/
Author: Anthony K GROSS
Author-email: anthony.k.gross@gmail.com
License: UNKNOWN
Project-URL: Documentation, https://anthonykgross.fr/python-workflow/
Project-URL: Source, https://github.com/anthonykgross/python-workflow/
Platform: UNKNOWN
Classifier: Programming Language :: Python :: 3
Classifier: License :: OSI Approved :: MIT License
Classifier: Operating System :: OS Independent
Requires-Python: >=3.8
License-File: LICENSE
Requires-Dist: gevent
